osm_map_merger/__init__.py
osm_map_merger/__main__.py
osm_map_merger/id_collector.py
osm_map_merger/id_generator.py
osm_map_merger/util.py
osm_map_merger-2025.1.dist-info/LICENSE
osm_map_merger-2025.1.dist-info/METADATA
osm_map_merger-2025.1.dist-info/WHEEL
osm_map_merger-2025.1.dist-info/entry_points.txt
osm_map_merger-2025.1.dist-info/top_level.txt
osm_map_merger-2025.1.dist-info/RECORD
