Metadata-Version: 2.1
Name: osm-map-merger
Version: 2025.1
Summary: Tool for handling (negative) IDs and merging different OSM maps (e.g. Lanelet2 maps). Very helpful if you have modeled several maps separately and now want to merge them into a single map.
Author-email: "Institute of Automotive Engineering, Technical University of Darmstadt" <open-source@fzd.tu-darmstadt.de>
Maintainer-email: "Institute of Automotive Engineering, Technical University of Darmstadt" <open-source@fzd.tu-darmstadt.de>
License: Copyright 2024 Institute of Automotive Engineering (FZD), Technical University of Darmstadt
Project-URL: BSSD-Homepage, https://gitlab.com/tuda-fzd/scenery-representations-and-maps/behavior-semantic-scenery-description
Project-URL: Repository, https://gitlab.com/tuda-fzd/scenery-representations-and-maps/osm-map-merger
Keywords: automated driving,BSSD,Lanelet2,OSM
Classifier: License :: OSI Approved :: MIT License
Classifier: Programming Language :: Python
Classifier: Programming Language :: Python :: 3
Requires-Python: >=3.8
License-File: LICENSE
Requires-Dist: osmium>=3.2.0
Requires-Dist: lxml
Requires-Dist: beautifulsoup4
Requires-Dist: click
Provides-Extra: dev
Requires-Dist: pytest; extra == "dev"
